{
  "model_params": {
    "kappa": 8.0,
    "sigma_X": 0.03162277660168379,
    "sigma_Y": 0.5872981252609742,
    "rho": 0.8869658170043403,
    "mu": 0.1
  },
  "predictions": "[55.58459949 55.59078437]",
  "trading_decisions": {
    "signals_t1": "[-1.]",
    "target_w_t1": "[-0.3  0. ]",
    "orders_t1": [],
    "signals_t2": "[-1.]",
    "target_w_t2": "[ 0.  -0.3]",
    "orders_t2": []
  },
  "market_data": {
    "F_mkt_t": "tenor_1    56.71\ntenor_2    63.98\nName: 2015-04-16 00:00:00, dtype: float64",
    "actual_F_mkt_t": "tenor_1    55.74\ntenor_2    63.45\nName: 2015-04-17 00:00:00, dtype: float64",
    "ttm_t": "tenor_1    0.083333\ntenor_2    0.166667\nName: 2015-04-16 00:00:00, dtype: float64",
    "mispricing": "[-1.12540051 -8.38921563]"
  },
  "performance": {
    "portfolio_value_t1": 100021.54042569967,
    "portfolio_value_t2": 84216.71584449185,
    "num_trades_t1": 0,
    "num_trades_t2": 0
  }
}