{
  "model_params": {
    "kappa": 0.1,
    "sigma_X": 0.10876374860610884,
    "sigma_Y": 0.39019205063754264,
    "rho": 0.3,
    "mu": -0.1
  },
  "predictions": "[104.62793434 104.58021388]",
  "trading_decisions": {
    "signals": "[ 1. -1.]",
    "target_weights": "[ 0.3 -0.3]",
    "orders": [],
    "z_scores": []
  },
  "market_data": {
    "F_mkt_t": "tenor_1     96.15\ntenor_2    113.59\nName: 2012-08-24 00:00:00, dtype: float64",
    "actual_F_mkt_t": "tenor_1     95.47\ntenor_2    112.26\nName: 2012-08-27 00:00:00, dtype: float64",
    "ttm_t": "tenor_1    0.083333\ntenor_2    0.166667\nName: 2012-08-24 00:00:00, dtype: float64",
    "mispricing": "[ 8.47793434 -9.00978612]"
  },
  "performance": {
    "portfolio_value": 91799.95748653055,
    "daily_pnl": 127.5116315209159,
    "gross_pnl": 127.5116315209159,
    "transaction_costs": 0.0,
    "num_trades": 0
  }
}