{
  "model_params": {
    "kappa": 0.1,
    "sigma_X": 0.8,
    "sigma_Y": 0.5,
    "rho": 0.3,
    "mu": 0.09014978729884514
  },
  "predictions": "[92.10359915 97.1981399 ]",
  "trading_decisions": {
    "signals": "[1. 1.]",
    "target_weights": "[0.3 0.3]",
    "orders": [],
    "z_scores": []
  },
  "market_data": {
    "F_mkt_t": "tenor_1    91.01\ntenor_2    93.42\nName: 2014-10-02 00:00:00, dtype: float64",
    "actual_F_mkt_t": "tenor_1    89.74\ntenor_2    92.31\nName: 2014-10-03 00:00:00, dtype: float64",
    "ttm_t": "tenor_1    0.083333\ntenor_2    0.166667\nName: 2014-10-02 00:00:00, dtype: float64",
    "mispricing": "[1.09359915 3.7781399 ]"
  },
  "performance": {
    "portfolio_value": 73110.599957657,
    "daily_pnl": -571.0995105037223,
    "gross_pnl": -571.0995105037223,
    "transaction_costs": 0.0,
    "num_trades": 0
  }
}