{
  "model_params": {
    "kappa": 5.0,
    "sigma_X": 0.09050900026649415,
    "sigma_Y": 0.01,
    "rho": -0.0704448450038968,
    "mu": 0.1
  },
  "predictions": "[46.42565027 46.80743174]",
  "trading_decisions": {
    "signals": "[1. 1.]",
    "target_weights": "[0.3 0.3]",
    "orders": [],
    "z_scores": []
  },
  "market_data": {
    "F_mkt_t": "tenor_1    44.66\ntenor_2    46.35\nName: 2016-11-03 00:00:00, dtype: float64",
    "actual_F_mkt_t": "tenor_1    44.07\ntenor_2    45.58\nName: 2016-11-04 00:00:00, dtype: float64",
    "ttm_t": "tenor_1    0.083333\ntenor_2    0.166667\nName: 2016-11-03 00:00:00, dtype: float64",
    "mispricing": "[1.76565027 0.45743174]"
  },
  "performance": {
    "portfolio_value": 3309.1453733577896,
    "daily_pnl": -29.874534571899122,
    "gross_pnl": -29.874534571899122,
    "transaction_costs": 0.0,
    "num_trades": 0
  }
}