{
  "model_params": {
    "kappa": 2.05338702636535,
    "sigma_X": 0.05,
    "sigma_Y": 0.01,
    "rho": 0.1,
    "mu": 0.09331200467185725
  },
  "predictions": "[61.36610525 61.82638613]",
  "trading_decisions": {
    "signals": "[ 1. -1.]",
    "target_weights": "[ 0.3 -0.3]",
    "orders": [],
    "z_scores": []
  },
  "market_data": {
    "F_mkt_t": "tenor_1    60.60\ntenor_2    64.36\nName: 2018-02-14 00:00:00, dtype: float64",
    "actual_F_mkt_t": "tenor_1    61.34\ntenor_2    64.33\nName: 2018-02-15 00:00:00, dtype: float64",
    "ttm_t": "tenor_1    0.083333\ntenor_2    0.166667\nName: 2018-02-14 00:00:00, dtype: float64",
    "mispricing": "[ 0.76610525 -2.53361387]"
  },
  "performance": {
    "portfolio_value": -9161.653309688563,
    "daily_pnl": -34.71162791677668,
    "gross_pnl": -34.71162791677668,
    "transaction_costs": 0.0,
    "num_trades": 0
  }
}