{
  "model_params": {
    "kappa": 5.0,
    "sigma_X": 0.05,
    "sigma_Y": 0.01,
    "rho": 0.3,
    "mu": -0.1
  },
  "predictions": "[67.69252008 67.13829139]",
  "trading_decisions": {
    "signals": "[ 1. -1.]",
    "target_weights": "[ 0.3 -0.3]",
    "orders": [],
    "z_scores": []
  },
  "market_data": {
    "F_mkt_t": "tenor_1    63.58\ntenor_2    70.83\nName: 2019-04-11 00:00:00, dtype: float64",
    "actual_F_mkt_t": "tenor_1    63.89\ntenor_2    71.55\nName: 2019-04-12 00:00:00, dtype: float64",
    "ttm_t": "tenor_1    0.083333\ntenor_2    0.166667\nName: 2019-04-11 00:00:00, dtype: float64",
    "mispricing": "[ 4.11252008 -3.69170861]"
  },
  "performance": {
    "portfolio_value": -12357.284270110167,
    "daily_pnl": 19.64008906613081,
    "gross_pnl": 19.64008906613081,
    "transaction_costs": 0.0,
    "num_trades": 0
  }
}