{
  "model_params": {
    "kappa": 0.1,
    "sigma_X": 0.8,
    "sigma_Y": 0.5,
    "rho": 0.1,
    "mu": 0.015212916250662609
  },
  "predictions": "[55.16492548 57.43018229]",
  "trading_decisions": {
    "signals": "[ 1. -1.]",
    "target_weights": "[ 0.3 -0.3]",
    "orders": [],
    "z_scores": []
  },
  "market_data": {
    "F_mkt_t": "tenor_1    53.31\ntenor_2    61.32\nName: 2019-01-29 00:00:00, dtype: float64",
    "actual_F_mkt_t": "tenor_1    54.23\ntenor_2    61.65\nName: 2019-01-30 00:00:00, dtype: float64",
    "ttm_t": "tenor_1    0.083333\ntenor_2    0.166667\nName: 2019-01-29 00:00:00, dtype: float64",
    "mispricing": "[ 1.85492548 -3.88981771]"
  },
  "performance": {
    "portfolio_value": -12296.811652572842,
    "daily_pnl": -43.65534488602472,
    "gross_pnl": -43.65534488602472,
    "transaction_costs": 0.0,
    "num_trades": 0
  }
}