{
  "model_params": {
    "kappa": 0.1,
    "sigma_X": 0.06530608914391141,
    "sigma_Y": 0.4642139062227526,
    "rho": -0.1712817485923727,
    "mu": -0.1
  },
  "predictions": "[41.97897532 41.99476198]",
  "trading_decisions": {
    "signals": "[ 1. -1.]",
    "target_weights": "[ 0.3 -0.3]",
    "orders": [
      [
        0,
        "BUY",
        0.6
      ]
    ],
    "z_scores": []
  },
  "market_data": {
    "F_mkt_t": "tenor_1    41.45\ntenor_2    43.80\nName: 2020-11-11 00:00:00, dtype: float64",
    "actual_F_mkt_t": "tenor_1    41.12\ntenor_2    43.53\nName: 2020-11-12 00:00:00, dtype: float64",
    "ttm_t": "tenor_1    0.083333\ntenor_2    0.166667\nName: 2020-11-11 00:00:00, dtype: float64",
    "mispricing": "[ 0.52897532 -1.80523802]"
  },
  "performance": {
    "portfolio_value": -5095.67730455921,
    "daily_pnl": -151.74606969672416,
    "gross_pnl": -20.95106969672417,
    "transaction_costs": 130.795,
    "num_trades": 1
  }
}