{
  "model_params": {
    "kappa": 0.1,
    "sigma_X": 0.6070289872266744,
    "sigma_Y": 0.5,
    "rho": 0.1,
    "mu": -0.1
  },
  "predictions": "[81.35402161 82.91913745]",
  "trading_decisions": {
    "signals": "[ 1. -1.]",
    "target_weights": "[ 0.3 -0.3]",
    "orders": [],
    "z_scores": []
  },
  "market_data": {
    "F_mkt_t": "tenor_1    80.86\ntenor_2    84.77\nName: 2023-04-18 00:00:00, dtype: float64",
    "actual_F_mkt_t": "tenor_1    79.16\ntenor_2    83.12\nName: 2023-04-19 00:00:00, dtype: float64",
    "ttm_t": "tenor_1    0.083333\ntenor_2    0.166667\nName: 2023-04-18 00:00:00, dtype: float64",
    "mispricing": "[ 0.49402161 -1.85086255]"
  },
  "performance": {
    "portfolio_value": -139672.0341671656,
    "daily_pnl": 65.37861827558231,
    "gross_pnl": 65.37861827558231,
    "transaction_costs": 0.0,
    "num_trades": 0
  }
}