{
  "model_params": {
    "kappa": 5.0,
    "sigma_X": 0.7172238770933662,
    "sigma_Y": 0.01,
    "rho": 0.4779268890893037,
    "mu": 0.08828764865824665
  },
  "predictions": "[77.56793071 78.68786717]",
  "trading_decisions": {
    "signals": "[ 1. -1.]",
    "target_weights": "[ 0.3 -0.3]",
    "orders": [],
    "z_scores": []
  },
  "market_data": {
    "F_mkt_t": "tenor_1    75.53\ntenor_2    79.62\nName: 2024-06-07 00:00:00, dtype: float64",
    "actual_F_mkt_t": "tenor_1    77.74\ntenor_2    81.63\nName: 2024-06-10 00:00:00, dtype: float64",
    "ttm_t": "tenor_1    0.083333\ntenor_2    0.166667\nName: 2024-06-07 00:00:00, dtype: float64",
    "mispricing": "[ 2.03793071 -0.93213283]"
  },
  "performance": {
    "portfolio_value": -215007.4736484569,
    "daily_pnl": -258.66387137460424,
    "gross_pnl": -258.66387137460424,
    "transaction_costs": 0.0,
    "num_trades": 0
  }
}