{
  "model_params": {
    "kappa": 8.0,
    "sigma_X": 0.03162277660168379,
    "sigma_Y": 0.3896766094432402,
    "rho": 0.9,
    "mu": -0.07494666598996032
  },
  "predictions": "[72.0413508  72.04164542]",
  "trading_decisions": {
    "signals": "[ 1. -1.]",
    "target_weights": "[ 0.3 -0.3]",
    "orders": [
      [
        1,
        "SELL",
        0.6
      ]
    ],
    "z_scores": []
  },
  "market_data": {
    "F_mkt_t": "tenor_1    69.42\ntenor_2    74.29\nName: 2023-06-13 00:00:00, dtype: float64",
    "actual_F_mkt_t": "tenor_1    68.27\ntenor_2    73.20\nName: 2023-06-14 00:00:00, dtype: float64",
    "ttm_t": "tenor_1    0.083333\ntenor_2    0.166667\nName: 2023-06-13 00:00:00, dtype: float64",
    "mispricing": "[ 2.6213508  -2.24835458]"
  },
  "performance": {
    "portfolio_value": -7277.225291607141,
    "daily_pnl": 174.61016472424242,
    "gross_pnl": 393.0951647242424,
    "transaction_costs": 218.48499999999999,
    "num_trades": 1
  }
}