{
  "model_params": {
    "kappa": 5.325068323953293,
    "sigma_X": 0.03162277660168379,
    "sigma_Y": 0.244996042748823,
    "rho": 0.9,
    "mu": 0.1
  },
  "predictions": "[90.04380147 90.02623772]",
  "trading_decisions": {
    "signals": "[-1. -1.]",
    "target_weights": "[-0.3 -0.3]",
    "orders": [],
    "z_scores": []
  },
  "market_data": {
    "F_mkt_t": "tenor_1    91.48\ntenor_2    94.43\nName: 2023-09-18 00:00:00, dtype: float64",
    "actual_F_mkt_t": "tenor_1    91.20\ntenor_2    94.34\nName: 2023-09-19 00:00:00, dtype: float64",
    "ttm_t": "tenor_1    0.083333\ntenor_2    0.166667\nName: 2023-09-18 00:00:00, dtype: float64",
    "mispricing": "[-1.43619853 -4.40376228]"
  },
  "performance": {
    "portfolio_value": -2350.299216896577,
    "daily_pnl": 314.33439881304037,
    "gross_pnl": 314.33439881304037,
    "transaction_costs": 0.0,
    "num_trades": 0
  }
}