{
  "model_params": {
    "kappa": 8.0,
    "sigma_X": 0.03162277660168379,
    "sigma_Y": 0.3389857357294681,
    "rho": 0.9,
    "mu": 0.1
  },
  "predictions": "[83.16532635 83.14426123]",
  "trading_decisions": {
    "signals": "[-1. -1.]",
    "target_weights": "[-0.3 -0.3]",
    "orders": [],
    "z_scores": []
  },
  "market_data": {
    "F_mkt_t": "tenor_1    84.40\ntenor_2    87.55\nName: 2023-08-09 00:00:00, dtype: float64",
    "actual_F_mkt_t": "tenor_1    82.82\ntenor_2    86.40\nName: 2023-08-10 00:00:00, dtype: float64",
    "ttm_t": "tenor_1    0.083333\ntenor_2    0.166667\nName: 2023-08-09 00:00:00, dtype: float64",
    "mispricing": "[-1.23467365 -4.40573877]"
  },
  "performance": {
    "portfolio_value": -6890.457113483211,
    "daily_pnl": 399.19318753945913,
    "gross_pnl": 399.19318753945913,
    "transaction_costs": 0.0,
    "num_trades": 0
  }
}