{
  "model_params": {
    "kappa": 8.0,
    "sigma_X": 0.03162277660168379,
    "sigma_Y": 0.28945673474943295,
    "rho": 0.9,
    "mu": -0.1
  },
  "predictions": "[77.26322507 77.26427924]",
  "trading_decisions": {
    "signals": "[-1. -1.]",
    "target_weights": "[-0.3 -0.3]",
    "orders": [
      [
        0,
        "SELL",
        0.3
      ]
    ],
    "z_scores": []
  },
  "market_data": {
    "F_mkt_t": "tenor_1    80.06\ntenor_2    82.30\nName: 2024-08-12 00:00:00, dtype: float64",
    "actual_F_mkt_t": "tenor_1    78.35\ntenor_2    80.69\nName: 2024-08-13 00:00:00, dtype: float64",
    "ttm_t": "tenor_1    0.083333\ntenor_2    0.166667\nName: 2024-08-12 00:00:00, dtype: float64",
    "mispricing": "[-2.79677493 -5.03572076]"
  },
  "performance": {
    "portfolio_value": -6223.977540153623,
    "daily_pnl": -84.81419860452444,
    "gross_pnl": 39.87580139547556,
    "transaction_costs": 124.69,
    "num_trades": 1
  }
}