{
  "model_params": {
    "kappa": 0.1,
    "sigma_X": 0.8,
    "sigma_Y": 0.5,
    "rho": 0.3,
    "mu": 0.1
  },
  "predictions": "[75.36825096 79.54682908]",
  "trading_decisions": {
    "signals": "[ 0. -1.]",
    "target_weights": "[ 0.  -0.3]",
    "orders": [
      [
        0,
        "SELL",
        0.3
      ]
    ],
    "z_scores": []
  },
  "market_data": {
    "F_mkt_t": "tenor_1    75.39\ntenor_2    80.68\nName: 2022-12-13 00:00:00, dtype: float64",
    "actual_F_mkt_t": "tenor_1    77.28\ntenor_2    82.70\nName: 2022-12-14 00:00:00, dtype: float64",
    "ttm_t": "tenor_1    0.083333\ntenor_2    0.166667\nName: 2022-12-13 00:00:00, dtype: float64",
    "mispricing": "[-0.02174904 -1.13317092]"
  },
  "performance": {
    "portfolio_value": 89928.83097332627,
    "daily_pnl": -119.09577682167883,
    "gross_pnl": 0.8767231783211855,
    "transaction_costs": 119.97250000000001,
    "num_trades": 1
  }
}