{
  "model_params": {
    "kappa": 0.1,
    "sigma_X": 0.8,
    "sigma_Y": 0.5,
    "rho": 0.17474717860908492,
    "mu": -0.07296353729666535
  },
  "predictions": "[78.26406699 81.16598228]",
  "trading_decisions": {
    "signals": "[-1. -1.]",
    "target_weights": "[-0.3 -0.3]",
    "orders": [],
    "z_scores": []
  },
  "market_data": {
    "F_mkt_t": "tenor_1    78.76\ntenor_2    82.73\nName: 2023-04-24 00:00:00, dtype: float64",
    "actual_F_mkt_t": "tenor_1    77.07\ntenor_2    80.77\nName: 2023-04-25 00:00:00, dtype: float64",
    "ttm_t": "tenor_1    0.083333\ntenor_2    0.166667\nName: 2023-04-24 00:00:00, dtype: float64",
    "mispricing": "[-0.49593301 -1.56401772]"
  },
  "performance": {
    "portfolio_value": 87788.94734511893,
    "daily_pnl": 1173.1875822672137,
    "gross_pnl": 1173.1875822672137,
    "transaction_costs": 0.0,
    "num_trades": 0
  }
}