{
  "model_params": {
    "kappa": 5.0,
    "sigma_X": 0.05,
    "sigma_Y": 0.01,
    "rho": 0.3,
    "mu": -0.1
  },
  "predictions": "[90.223749   89.48625679]",
  "trading_decisions": {
    "signals": "[ 1. -1.]",
    "target_weights": "[ 0.3 -0.3]",
    "orders": [
      [
        0,
        "BUY",
        0.6
      ]
    ],
    "z_scores": []
  },
  "market_data": {
    "F_mkt_t": "tenor_1    88.75\ntenor_2    92.16\nName: 2023-10-20 00:00:00, dtype: float64",
    "actual_F_mkt_t": "tenor_1    85.49\ntenor_2    89.83\nName: 2023-10-23 00:00:00, dtype: float64",
    "ttm_t": "tenor_1    0.083333\ntenor_2    0.166667\nName: 2023-10-20 00:00:00, dtype: float64",
    "mispricing": "[ 1.473749   -2.67374321]"
  },
  "performance": {
    "portfolio_value": 76229.0735862619,
    "daily_pnl": 1123.0146867714056,
    "gross_pnl": 1397.2996867714057,
    "transaction_costs": 274.285,
    "num_trades": 1
  }
}