{
  "model_params": {
    "kappa": 8.0,
    "sigma_X": 0.03162277660168379,
    "sigma_Y": 0.13765291670323207,
    "rho": 0.73916711956991,
    "mu": 0.07046221299591716
  },
  "predictions": "[105.38793843 105.38350804]",
  "trading_decisions": {
    "signals_t1": "[1.]",
    "target_w_t1": "[0.3 0. ]",
    "orders_t1": [],
    "signals_t2": "[-1.]",
    "target_w_t2": "[ 0.  -0.3]",
    "orders_t2": []
  },
  "market_data": {
    "F_mkt_t": "tenor_1    104.42\ntenor_2    107.33\nName: 2014-07-22 00:00:00, dtype: float64",
    "actual_F_mkt_t": "tenor_1    103.12\ntenor_2    108.03\nName: 2014-07-23 00:00:00, dtype: float64",
    "ttm_t": "tenor_1    0.083333\ntenor_2    0.166667\nName: 2014-07-22 00:00:00, dtype: float64",
    "mispricing": "[ 0.96793843 -1.94649196]"
  },
  "performance": {
    "portfolio_value_t1": 102480.43198203146,
    "portfolio_value_t2": 99753.33172705537,
    "num_trades_t1": 0,
    "num_trades_t2": 0
  }
}