{
  "model_params": {
    "kappa": 3.646785000151853,
    "sigma_X": 0.8245785883260114,
    "sigma_Y": 0.1829691937893576,
    "rho": -0.99,
    "mu": 0.1
  },
  "predictions": "[ 90.40977836 114.77619729]",
  "trading_decisions": {
    "signals": "[1. 1.]",
    "target_weights": "[0.3 0.3]",
    "orders": [],
    "z_scores": []
  },
  "market_data": {
    "F_mkt_t": "tenor_1     85.09\ntenor_2    107.25\nName: 2012-11-08 00:00:00, dtype: float64",
    "actual_F_mkt_t": "tenor_1     86.07\ntenor_2    109.40\nName: 2012-11-09 00:00:00, dtype: float64",
    "ttm_t": "tenor_1    0.083333\ntenor_2    0.166667\nName: 2012-11-08 00:00:00, dtype: float64",
    "mispricing": "[5.31977836 7.52619729]"
  },
  "performance": {
    "portfolio_value": 88191.39792535777,
    "daily_pnl": 827.2641860052681,
    "gross_pnl": 827.2641860052681,
    "transaction_costs": 0.0,
    "num_trades": 0
  }
}