{
  "model_params": {
    "kappa": 0.10000000000000009,
    "sigma_X": 0.05,
    "sigma_Y": 0.01,
    "rho": -0.4404409401191214,
    "mu": -0.1
  },
  "predictions": "[112.94712221 112.02017435]",
  "trading_decisions": {
    "signals": "[ 1. -1.]",
    "target_weights": "[ 0.3 -0.3]",
    "orders": [],
    "z_scores": []
  },
  "market_data": {
    "F_mkt_t": "tenor_1    106.28\ntenor_2    122.90\nName: 2012-02-22 00:00:00, dtype: float64",
    "actual_F_mkt_t": "tenor_1    107.83\ntenor_2    123.62\nName: 2012-02-23 00:00:00, dtype: float64",
    "ttm_t": "tenor_1    0.083333\ntenor_2    0.166667\nName: 2012-02-22 00:00:00, dtype: float64",
    "mispricing": "[  6.66712221 -10.87982565]"
  },
  "performance": {
    "portfolio_value": 98591.97724005912,
    "daily_pnl": 257.4112570890631,
    "gross_pnl": 257.4112570890631,
    "transaction_costs": 0.0,
    "num_trades": 0
  }
}