{
  "model_params": {
    "kappa": 2.2228393659944765,
    "sigma_X": 0.2585003469987929,
    "sigma_Y": 0.07755020980676931,
    "rho": 0.799999636276536,
    "mu": -0.09999998878442207
  },
  "predictions": "[0.84799866 0.8564541 ]",
  "trading_decisions": {
    "signals": "[-1. -1.]",
    "target_weights": "[-0.3 -0.3]",
    "orders": [],
    "z_scores": []
  },
  "market_data": {
    "F_mkt_t": "tenor_1    69.15\ntenor_2    72.69\nName: 2024-09-05 00:00:00, dtype: float64",
    "actual_F_mkt_t": "tenor_1    67.67\ntenor_2    71.06\nName: 2024-09-06 00:00:00, dtype: float64",
    "ttm_t": "tenor_1    0.083333\ntenor_2    0.166667\nName: 2024-09-05 00:00:00, dtype: float64",
    "mispricing": "[-68.30200134 -71.8335459 ]"
  },
  "performance": {
    "portfolio_value": 111963.71390756393,
    "daily_pnl": 1452.997330997105,
    "gross_pnl": 1452.997330997105,
    "transaction_costs": 0.0,
    "num_trades": 0
  }
}