{
  "model_params": {
    "kappa": 8.0,
    "sigma_X": 0.48644273603147775,
    "sigma_Y": 0.21560215596514698,
    "rho": 0.9,
    "mu": -0.1
  },
  "predictions": "[77.56547879 77.54104376]",
  "trading_decisions": {
    "signals_t1": "[1.]",
    "target_w_t1": "[0.3 0. ]",
    "orders_t1": [],
    "signals_t2": "[-1.]",
    "target_w_t2": "[ 0.  -0.3]",
    "orders_t2": []
  },
  "market_data": {
    "F_mkt_t": "tenor_1    75.55\ntenor_2    79.87\nName: 2024-06-06 00:00:00, dtype: float64",
    "actual_F_mkt_t": "tenor_1    75.53\ntenor_2    79.62\nName: 2024-06-07 00:00:00, dtype: float64",
    "ttm_t": "tenor_1    0.083333\ntenor_2    0.166667\nName: 2024-06-06 00:00:00, dtype: float64",
    "mispricing": "[ 2.01547879 -2.32895624]"
  },
  "performance": {
    "portfolio_value_t1": 115973.69882336489,
    "portfolio_value_t2": 131988.27404803736,
    "num_trades_t1": 0,
    "num_trades_t2": 0
  }
}